tensorflow_compression/LICENSE
tensorflow_compression/README.md
tensorflow_compression/__init__.py
tensorflow_compression/all_tests.py
tensorflow_compression/cc/libtensorflow_compression.so
tensorflow_compression/python/__init__.py
tensorflow_compression/python/datasets/__init__.py
tensorflow_compression/python/datasets/y4m_dataset.py
tensorflow_compression/python/datasets/y4m_dataset_test.py
tensorflow_compression/python/distributions/__init__.py
tensorflow_compression/python/distributions/deep_factorized.py
tensorflow_compression/python/distributions/deep_factorized_test.py
tensorflow_compression/python/distributions/helpers.py
tensorflow_compression/python/distributions/helpers_test.py
tensorflow_compression/python/distributions/round_adapters.py
tensorflow_compression/python/distributions/round_adapters_test.py
tensorflow_compression/python/distributions/uniform_noise.py
tensorflow_compression/python/distributions/uniform_noise_test.py
tensorflow_compression/python/entropy_models/__init__.py
tensorflow_compression/python/entropy_models/continuous_base.py
tensorflow_compression/python/entropy_models/continuous_batched.py
tensorflow_compression/python/entropy_models/continuous_batched_test.py
tensorflow_compression/python/entropy_models/continuous_indexed.py
tensorflow_compression/python/entropy_models/continuous_indexed_test.py
tensorflow_compression/python/entropy_models/laplace.py
tensorflow_compression/python/entropy_models/laplace_test.py
tensorflow_compression/python/entropy_models/power_law.py
tensorflow_compression/python/entropy_models/power_law_test.py
tensorflow_compression/python/entropy_models/universal.py
tensorflow_compression/python/entropy_models/universal_test.py
tensorflow_compression/python/layers/__init__.py
tensorflow_compression/python/layers/gdn.py
tensorflow_compression/python/layers/gdn_test.py
tensorflow_compression/python/layers/initializers.py
tensorflow_compression/python/layers/initializers_test.py
tensorflow_compression-2.14.1.dist-info/METADATA
tensorflow_compression-2.14.1.dist-info/WHEEL
tensorflow_compression-2.14.1.dist-info/top_level.txt
tensorflow_compression-2.14.1.dist-info/RECORD
